answer_book_mcp.py
answer_book_mcp-1.0.0.dist-info/METADATA
answer_book_mcp-1.0.0.dist-info/WHEEL
answer_book_mcp-1.0.0.dist-info/entry_points.txt
answer_book_mcp-1.0.0.dist-info/top_level.txt
answer_book_mcp-1.0.0.dist-info/RECORD
