Metadata-Version: 2.4
Name: answer-book-mcp
Version: 1.0.0
Summary: 一本智慧之书 MCP 服务，为问题提供随机而富有哲理的答案
Requires-Python: >=3.10
Requires-Dist: mcp>=1.0.0
Requires-Dist: fastapi>=0.104.0
Requires-Dist: uvicorn>=0.24.0
Requires-Dist: uv>=0.1.15
Requires-Dist: build>=1.3.0
Requires-Dist: twine>=6.2.0
